{
	"name": "V_RptParcelLevel_CENSorter",
	"properties": {
		"folder": {
			"name": "Structured Schema on Read/Reports/Views"
		},
		"content": {
			"query": "IF EXISTS ( SELECT * FROM sys.views WHERE object_id = OBJECT_ID('dbo.V_RptParcelLevel_CENSorter') )\n    DROP VIEW dbo.V_RptParcelLevel_CENSorter\nGO\n\nCREATE VIEW [dbo].[V_RptParcelLevel_CENSorter]\n\nAS \n\n\nSELECT \nlms_cenplclpnrouting_id as id\n,lms_cenplclpnrouting_autosystemid\n,lms_cenplclpnrouting_lpn\n,lms_cenplclpnrouting_status\n,lms_cenplclpnrouting_datereceived\n,lms_cenplclpnrouting_dateupdated\n,lms_cenplclpnrouting_plcdivertid\n,lms_cenplclpnrouting_cldivertid\n,lms_cenplclpnrouting_divertdescription\n,lms_parcel_orderbillcustname\n,lms_parcel_orderdelivercustcref\n,lms_parcel_orderdelivercustname\n,lms_parcel_orderdelivercustsrouteid\nFROM dbo.RptParcelLevel \nWHERE lms_cenplclpnrouting_id IS NOT NULL\n\n",
			"metadata": {
				"language": "sql"
			},
			"currentConnection": {
				"databaseName": "RPT",
				"poolName": "Built-in"
			},
			"resultLimit": 5000
		},
		"type": "SqlQuery"
	}
}